meshql/__init__.py
meshql/entity.py
meshql/ql.py
meshql/transaction.py
meshql/visualizer.py
meshql/mesh/__init__.py
meshql/mesh/exporters.py
meshql/mesh/importers.py
meshql/mesh/mesh.py
meshql/preprocessing/__init__.py
meshql/preprocessing/split.py
meshql/transactions/__init__.py
meshql/transactions/algorithm.py
meshql/transactions/boundary_layer.py
meshql/transactions/physical_group.py
meshql/transactions/refinement.py
meshql/transactions/transfinite.py
meshql/utils/cq.py
meshql/utils/plot.py
meshql/utils/shapes.py
meshql/utils/types.py
meshql-1.0.0.dist-info/LICENSE
meshql-1.0.0.dist-info/METADATA
meshql-1.0.0.dist-info/WHEEL
meshql-1.0.0.dist-info/top_level.txt
meshql-1.0.0.dist-info/RECORD
