Metadata-Version: 2.1
Name: meshql
Version: 1.0.0
Summary: query based meshing on top of GMSH
Author: Afshawn Lotfi
Author-email: 
License-File: LICENSE
Requires-Dist: numpy
Requires-Dist: gmsh
Requires-Dist: ipywidgets ==7.6
Requires-Dist: ipython-genutils
Requires-Dist: pythreejs
Requires-Dist: su2fmt ==2.0.0
Requires-Dist: shapely
Requires-Dist: scipy
Requires-Dist: jupyter-cadquery
